pgp_check/__init__.py
pgp_check/cli.py
python_pgp_check-0.3.2.dist-info/METADATA
python_pgp_check-0.3.2.dist-info/WHEEL
python_pgp_check-0.3.2.dist-info/entry_points.txt
python_pgp_check-0.3.2.dist-info/top_level.txt
python_pgp_check-0.3.2.dist-info/RECORD
