Metadata-Version: 2.2
Name: python-pgp-check
Version: 0.3.2
Summary: A CLI tool to verify file hashes
Home-page: https://github.com/iiroan/python-pgp-check
Author: IRoan
Author-email: pypi@lunary.roan.zip
Classifier: Programming Language :: Python :: 3
Classifier: License :: OSI Approved :: MIT License
Classifier: Operating System :: OS Independent
Requires-Python: >=3.6
Dynamic: author
Dynamic: author-email
Dynamic: classifier
Dynamic: description
Dynamic: description-content-type
Dynamic: home-page
Dynamic: requires-python
Dynamic: summary
